CLSearch/__init__.py
CLSearch/command.py
CLSearch/config.py
CLSearch/database.py
CLSearch/dicts.py
CLSearch/message.py
CLSearch/scratch.py
CLSearch/shell.py
CLSearch/utilities.py
CLSearch/templates/_listing.html
CLSearch/templates/base.html
CLSearch/templates/base.txt
tests/__init__.py
tests/integration_test.py
tests/test_command.py
tests/test_database.py
vehicular/__init__.py
vehicular/__main__.py
vehicular/command.py
vehicular/config.py
vehicular/database.py
vehicular/dicts.py
vehicular/main.py
vehicular/message.py
vehicular/scratch.py
vehicular/shell.py
vehicular/utilities.py
vehicular/templates/_listing.html
vehicular/templates/base.html
vehicular/templates/base.txt
vehicular-0.1.0.data/data/vehicular/templates/_listing.html
vehicular-0.1.0.data/data/vehicular/templates/base.html
vehicular-0.1.0.data/data/vehicular/templates/base.txt
vehicular-0.1.0.dist-info/METADATA
vehicular-0.1.0.dist-info/RECORD
vehicular-0.1.0.dist-info/WHEEL
vehicular-0.1.0.dist-info/entry_points.txt
vehicular-0.1.0.dist-info/top_level.txt
