Metadata-Version: 2.1
Name: vehicular
Version: 0.1.0
Summary: a craigslist vehicle search cli app
Home-page: https://github.com/jakkso/vehicular
Author: Alexander Potts
Author-email: alexander.potts@gmail.com
License: UNKNOWN
Platform: UNKNOWN
Classifier: Development Status :: 4 - Beta
Classifier: Programming Language :: Python :: 3.6
Classifier: License :: OSI Approved :: GNU General Public License v3 (GPLv3)
Classifier: Operating System :: MacOS
Classifier: Operating System :: POSIX :: Linux
Classifier: Programming Language :: Python :: 3 :: Only 
Classifier: Topic :: Utilities
Requires-Dist: feedparser
Requires-Dist: jinja2
Requires-Dist: gnureadline
